bullion/__init__.py
bullion/bullion.py
bullion/bullionstar.py
bullion/silverbullion.py
bullion/stargrams.py
singapore_bullion_retailers_api-0.0.1.dist-info/METADATA
singapore_bullion_retailers_api-0.0.1.dist-info/WHEEL
singapore_bullion_retailers_api-0.0.1.dist-info/top_level.txt
singapore_bullion_retailers_api-0.0.1.dist-info/RECORD
